{
    "/js/admin.js": "/js/admin.js",
    "/js/admin.js.map": "/js/admin.js.map",
    "/js/app.js": "/js/app.js",
    "/css/app.css": "/css/app.css",
    "/js/app.js.map": "/js/app.js.map",
    "/css/app.css.map": "/css/app.css.map",
    "/js/admin.0c4da2d5305429514ffe.hot-update.js": "/js/admin.0c4da2d5305429514ffe.hot-update.js",
    "/js/admin.0c4da2d5305429514ffe.hot-update.js.map": "/js/admin.0c4da2d5305429514ffe.hot-update.js.map",
    "/js/admin.9ffa31b19da5a8a563ad.hot-update.js": "/js/admin.9ffa31b19da5a8a563ad.hot-update.js",
    "/js/admin.9ffa31b19da5a8a563ad.hot-update.js.map": "/js/admin.9ffa31b19da5a8a563ad.hot-update.js.map",
    "/js/admin.3ee4a88a7c6cacf89ea1.hot-update.js": "/js/admin.3ee4a88a7c6cacf89ea1.hot-update.js",
    "/js/admin.3ee4a88a7c6cacf89ea1.hot-update.js.map": "/js/admin.3ee4a88a7c6cacf89ea1.hot-update.js.map",
    "/js/admin.a03aeadbc040d2ec3d0c.hot-update.js": "/js/admin.a03aeadbc040d2ec3d0c.hot-update.js",
    "/js/admin.a03aeadbc040d2ec3d0c.hot-update.js.map": "/js/admin.a03aeadbc040d2ec3d0c.hot-update.js.map",
    "/js/admin.4b2d25b9d13660914783.hot-update.js": "/js/admin.4b2d25b9d13660914783.hot-update.js",
    "/js/admin.4b2d25b9d13660914783.hot-update.js.map": "/js/admin.4b2d25b9d13660914783.hot-update.js.map",
    "/js/admin.4e99de94b0939fdbad08.hot-update.js": "/js/admin.4e99de94b0939fdbad08.hot-update.js",
    "/js/admin.4e99de94b0939fdbad08.hot-update.js.map": "/js/admin.4e99de94b0939fdbad08.hot-update.js.map",
    "/js/admin.92083024dcaebd817e2c.hot-update.js": "/js/admin.92083024dcaebd817e2c.hot-update.js",
    "/js/admin.92083024dcaebd817e2c.hot-update.js.map": "/js/admin.92083024dcaebd817e2c.hot-update.js.map",
    "/js/admin.9f88cab74ddad224f76c.hot-update.js": "/js/admin.9f88cab74ddad224f76c.hot-update.js",
    "/js/admin.9f88cab74ddad224f76c.hot-update.js.map": "/js/admin.9f88cab74ddad224f76c.hot-update.js.map",
    "/js/admin.b7443b65ae3b9cd737b6.hot-update.js": "/js/admin.b7443b65ae3b9cd737b6.hot-update.js",
    "/js/admin.b7443b65ae3b9cd737b6.hot-update.js.map": "/js/admin.b7443b65ae3b9cd737b6.hot-update.js.map",
    "/js/admin.a011b98768491a905f8e.hot-update.js": "/js/admin.a011b98768491a905f8e.hot-update.js",
    "/js/admin.a011b98768491a905f8e.hot-update.js.map": "/js/admin.a011b98768491a905f8e.hot-update.js.map",
    "/js/admin.92db89fd6c2c9874a9a2.hot-update.js": "/js/admin.92db89fd6c2c9874a9a2.hot-update.js",
    "/js/admin.92db89fd6c2c9874a9a2.hot-update.js.map": "/js/admin.92db89fd6c2c9874a9a2.hot-update.js.map",
    "/js/admin.53a102ad7759c614a4f0.hot-update.js": "/js/admin.53a102ad7759c614a4f0.hot-update.js",
    "/js/admin.53a102ad7759c614a4f0.hot-update.js.map": "/js/admin.53a102ad7759c614a4f0.hot-update.js.map",
    "/js/admin.d529b5cdf9f5da42dc8e.hot-update.js": "/js/admin.d529b5cdf9f5da42dc8e.hot-update.js",
    "/js/admin.d529b5cdf9f5da42dc8e.hot-update.js.map": "/js/admin.d529b5cdf9f5da42dc8e.hot-update.js.map",
    "/js/admin.4838ee74a564686809ef.hot-update.js": "/js/admin.4838ee74a564686809ef.hot-update.js",
    "/js/admin.4838ee74a564686809ef.hot-update.js.map": "/js/admin.4838ee74a564686809ef.hot-update.js.map",
    "/js/admin.19809b7ff8c753a2ff54.hot-update.js": "/js/admin.19809b7ff8c753a2ff54.hot-update.js",
    "/js/admin.19809b7ff8c753a2ff54.hot-update.js.map": "/js/admin.19809b7ff8c753a2ff54.hot-update.js.map",
    "/js/admin.2268a5956023e6ddac42.hot-update.js": "/js/admin.2268a5956023e6ddac42.hot-update.js",
    "/js/admin.2268a5956023e6ddac42.hot-update.js.map": "/js/admin.2268a5956023e6ddac42.hot-update.js.map",
    "/js/admin.fa9edd7af4418c2e504d.hot-update.js": "/js/admin.fa9edd7af4418c2e504d.hot-update.js",
    "/js/admin.fa9edd7af4418c2e504d.hot-update.js.map": "/js/admin.fa9edd7af4418c2e504d.hot-update.js.map",
    "/js/admin.02ed0cc39401aa6205aa.hot-update.js": "/js/admin.02ed0cc39401aa6205aa.hot-update.js",
    "/js/admin.02ed0cc39401aa6205aa.hot-update.js.map": "/js/admin.02ed0cc39401aa6205aa.hot-update.js.map",
    "/js/admin.3cf6e327c95e4365ca36.hot-update.js": "/js/admin.3cf6e327c95e4365ca36.hot-update.js",
    "/js/admin.3cf6e327c95e4365ca36.hot-update.js.map": "/js/admin.3cf6e327c95e4365ca36.hot-update.js.map"
}
